ncov/__init__.py
ncov/parser/Alleles.py
ncov/parser/Consensus.py
ncov/parser/Lineage.py
ncov/parser/Meta.py
ncov/parser/NegativeControl.py
ncov/parser/PerBaseCoverage.py
ncov/parser/Sites.py
ncov/parser/Snpeff.py
ncov/parser/Variants.py
ncov/parser/Vcf.py
ncov/parser/WatchList.py
ncov/parser/__init__.py
ncov/parser/primers.py
ncov/parser/qc.py
ncov_parser-0.7.0.data/scripts/collect_qc_summary.py
ncov_parser-0.7.0.data/scripts/get_qc.py
ncov_parser-0.7.0.data/scripts/primers_to_amplicons.py
ncov_parser-0.7.0.dist-info/LICENSE
ncov_parser-0.7.0.dist-info/METADATA
ncov_parser-0.7.0.dist-info/WHEEL
ncov_parser-0.7.0.dist-info/top_level.txt
ncov_parser-0.7.0.dist-info/RECORD
