Metadata-Version: 2.1
Name: ncov-parser
Version: 0.7.0
Summary: A nCoV package for parsing analysis files
Home-page: https://github.com/rdeborja/ncov_parser
Author: Richard J. de Borja
Author-email: richard.deborja@oicr.on.ca
License: MIT
Platform: UNKNOWN
Classifier: Programming Language :: Python :: 3
Classifier: License :: OSI Approved :: MIT License
Classifier: Operating System :: OS Independent
Requires-Python: >=3.6
License-File: LICENSE
